ainator/__about__.py
ainator/__init__.py
ainator/cli.py
ainator/configuration.py
ainator/renderer.py
ainator/server.py
ainator/db/README.md
ainator/db/sqlite.py
ainator/knowledge/code.py
ainator/knowledge/generic.py
ainator/knowledge/site.py
ainator/toolkits/chunked_shell.py
ainator-0.0.21.dist-info/METADATA
ainator-0.0.21.dist-info/WHEEL
ainator-0.0.21.dist-info/entry_points.txt
ainator-0.0.21.dist-info/licenses/LICENSE.txt
ainator-0.0.21.dist-info/RECORD
