Metadata-Version: 2.4
Name: ainator
Version: 0.0.21
Project-URL: Documentation, https://yourlabs.io/oss/ainator#readme
Project-URL: Issues, https://yourlabs.io/oss/ainator/issues
Project-URL: Source, https://yourlabs.io/oss/ainator
Author-email: jpic <jpic@yourlabs.org>
License-Expression: MIT
License-File: LICENSE.txt
Classifier: Development Status :: 4 - Beta
Classifier: Programming Language :: Python
Classifier: Programming Language :: Python :: 3.8
Classifier: Programming Language :: Python :: 3.9
Classifier: Programming Language :: Python :: 3.10
Classifier: Programming Language :: Python :: 3.11
Classifier: Programming Language :: Python :: 3.12
Classifier: Programming Language :: Python :: Implementation :: CPython
Classifier: Programming Language :: Python :: Implementation :: PyPy
Requires-Python: >=3.8
Requires-Dist: agno
Requires-Dist: cli2
Requires-Dist: ddgs
Requires-Dist: ebooklib
Requires-Dist: html2text
Requires-Dist: httpx
Requires-Dist: huggingface-hub
Requires-Dist: huggingface-hub<1.0,>=0.34.0
Requires-Dist: lancedb
Requires-Dist: llama-index-core
Requires-Dist: llama-index-embeddings-huggingface
Requires-Dist: llama-index-vector-stores-lancedb
Requires-Dist: openai
Requires-Dist: pandas
Requires-Dist: parsel
Requires-Dist: pygments
Requires-Dist: pyyaml
Requires-Dist: sentence-transformers>=5.1.0
Requires-Dist: transformers
Requires-Dist: tree-sitter
Requires-Dist: tree-sitter-language-pack
